{
  "version": 1,
  "updatedAt": "2026-03-11T19:15:42.331Z",
  "latest": {
    "runId": "d4e74dd4-cf8e-4e46-be23-c670bbede027",
    "reason": "scheduled",
    "startedAt": "2026-03-11T19:15:42.156Z",
    "finishedAt": "2026-03-11T19:15:42.331Z",
    "durationMs": 175,
    "overallStatus": "ok",
    "services": {
      "server": {
        "ok": true,
        "latencyMs": 174,
        "details": {
          "latencyMs": 152,
          "status": 200
        }
      },
      "opey": {
        "ok": true,
        "latencyMs": 9,
        "details": {
          "alive": true,
          "currentTicketId": null,
          "lastPollAt": 1773256518807
        }
      },
      "tidy": {
        "ok": true,
        "latencyMs": 9,
        "details": {
          "alive": true,
          "isProcessing": false,
          "lastTickAt": 1773256486342
        }
      },
      "telegram": {
        "ok": true,
        "latencyMs": 27,
        "details": {
          "transport": "telegram"
        }
      }
    },
    "summary": {
      "okCount": 4,
      "failCount": 0,
      "failingServices": []
    }
  },
  "history": [
    {
      "runId": "d4e74dd4-cf8e-4e46-be23-c670bbede027",
      "reason": "scheduled",
      "startedAt": "2026-03-11T19:15:42.156Z",
      "finishedAt": "2026-03-11T19:15:42.331Z",
      "durationMs": 175,
      "overallStatus": "ok",
      "services": {
        "server": {
          "ok": true,
          "latencyMs": 174,
          "details": {
            "latencyMs": 152,
            "status": 200
          }
        },
        "opey": {
          "ok": true,
          "latencyMs": 9,
          "details": {
            "alive": true,
            "currentTicketId": null,
            "lastPollAt": 1773256518807
          }
        },
        "tidy": {
          "ok": true,
          "latencyMs": 9,
          "details": {
            "alive": true,
            "isProcessing": false,
            "lastTickAt": 1773256486342
          }
        },
        "telegram": {
          "ok": true,
          "latencyMs": 27,
          "details": {
            "transport": "telegram"
          }
        }
      },
      "summary": {
        "okCount": 4,
        "failCount": 0,
        "failingServices": []
      }
    },
    {
      "runId": "5023e3f8-45ba-4916-9182-345fedca2d4a",
      "reason": "scheduled",
      "startedAt": "2026-03-11T19:14:45.196Z",
      "finishedAt": "2026-03-11T19:14:45.553Z",
      "durationMs": 357,
      "overallStatus": "ok",
      "services": {
        "server": {
          "ok": true,
          "latencyMs": 356,
          "details": {
            "latencyMs": 343,
            "status": 200
          }
        },
        "opey": {
          "ok": true,
          "latencyMs": 5,
          "details": {
            "alive": true,
            "currentTicketId": null,
            "lastPollAt": 1773256458793
          }
        },
        "tidy": {
          "ok": true,
          "latencyMs": 5,
          "details": {
            "alive": true,
            "isProcessing": false,
            "lastTickAt": 1773256426333
          }
        },
        "telegram": {
          "ok": true,
          "latencyMs": 18,
          "details": {
            "transport": "telegram"
          }
        }
      },
      "summary": {
        "okCount": 4,
        "failCount": 0,
        "failingServices": []
      }
    },
    {
      "runId": "1103a373-bdbf-404d-b653-4fd776ff0e56",
      "reason": "scheduled",
      "startedAt": "2026-03-11T19:04:45.187Z",
      "finishedAt": "2026-03-11T19:04:45.400Z",
      "durationMs": 213,
      "overallStatus": "ok",
      "services": {
        "server": {
          "ok": true,
          "latencyMs": 212,
          "details": {
            "latencyMs": 182,
            "status": 200
          }
        },
        "opey": {
          "ok": true,
          "latencyMs": 19,
          "details": {
            "alive": true,
            "currentTicketId": null,
            "lastPollAt": 1773255858637
          }
        },
        "tidy": {
          "ok": true,
          "latencyMs": 19,
          "details": {
            "alive": true,
            "isProcessing": false,
            "lastTickAt": 1773255826252
          }
        },
        "telegram": {
          "ok": true,
          "latencyMs": 33,
          "details": {
            "transport": "telegram"
          }
        }
      },
      "summary": {
        "okCount": 4,
        "failCount": 0,
        "failingServices": []
      }
    },
    {
      "runId": "9d639213-4b50-40e8-8088-84f6f4891df0",
      "reason": "scheduled",
      "startedAt": "2026-03-11T18:54:45.185Z",
      "finishedAt": "2026-03-11T18:54:45.357Z",
      "durationMs": 172,
      "overallStatus": "ok",
      "services": {
        "server": {
          "ok": true,
          "latencyMs": 171,
          "details": {
            "latencyMs": 159,
            "status": 200
          }
        },
        "opey": {
          "ok": true,
          "latencyMs": 7,
          "details": {
            "alive": true,
            "currentTicketId": null,
            "lastPollAt": 1773255258488
          }
        },
        "tidy": {
          "ok": true,
          "latencyMs": 6,
          "details": {
            "alive": true,
            "isProcessing": false,
            "lastTickAt": 1773255226190
          }
        },
        "telegram": {
          "ok": true,
          "latencyMs": 28,
          "details": {
            "transport": "telegram"
          }
        }
      },
      "summary": {
        "okCount": 4,
        "failCount": 0,
        "failingServices": []
      }
    },
    {
      "runId": "6f13214f-9311-48db-a1c2-82d6f9a6508d",
      "reason": "scheduled",
      "startedAt": "2026-03-11T18:44:45.173Z",
      "finishedAt": "2026-03-11T18:44:45.323Z",
      "durationMs": 150,
      "overallStatus": "ok",
      "services": {
        "server": {
          "ok": true,
          "latencyMs": 150,
          "details": {
            "latencyMs": 135,
            "status": 200
          }
        },
        "opey": {
          "ok": true,
          "latencyMs": 7,
          "details": {
            "alive": true,
            "currentTicketId": null,
            "lastPollAt": 1773254658338
          }
        },
        "tidy": {
          "ok": true,
          "latencyMs": 6,
          "details": {
            "alive": true,
            "isProcessing": false,
            "lastTickAt": 1773254626094
          }
        },
        "telegram": {
          "ok": true,
          "latencyMs": 21,
          "details": {
            "transport": "telegram"
          }
        }
      },
      "summary": {
        "okCount": 4,
        "failCount": 0,
        "failingServices": []
      }
    },
    {
      "runId": "3951601d-993f-4590-80db-d09731703a45",
      "reason": "scheduled",
      "startedAt": "2026-03-11T18:34:45.165Z",
      "finishedAt": "2026-03-11T18:34:45.368Z",
      "durationMs": 203,
      "overallStatus": "ok",
      "services": {
        "server": {
          "ok": true,
          "latencyMs": 203,
          "details": {
            "latencyMs": 192,
            "status": 200
          }
        },
        "opey": {
          "ok": true,
          "latencyMs": 6,
          "details": {
            "alive": true,
            "currentTicketId": null,
            "lastPollAt": 1773254058205
          }
        },
        "tidy": {
          "ok": true,
          "latencyMs": 6,
          "details": {
            "alive": true,
            "isProcessing": false,
            "lastTickAt": 1773254026003
          }
        },
        "telegram": {
          "ok": true,
          "latencyMs": 21,
          "details": {
            "transport": "telegram"
          }
        }
      },
      "summary": {
        "okCount": 4,
        "failCount": 0,
        "failingServices": []
      }
    },
    {
      "runId": "062ceef3-323b-4092-a73d-4abb6744d2d6",
      "reason": "scheduled",
      "startedAt": "2026-03-11T18:24:45.164Z",
      "finishedAt": "2026-03-11T18:24:45.325Z",
      "durationMs": 161,
      "overallStatus": "ok",
      "services": {
        "server": {
          "ok": true,
          "latencyMs": 161,
          "details": {
            "latencyMs": 149,
            "status": 200
          }
        },
        "opey": {
          "ok": true,
          "latencyMs": 6,
          "details": {
            "alive": true,
            "currentTicketId": null,
            "lastPollAt": 1773253458056
          }
        },
        "tidy": {
          "ok": true,
          "latencyMs": 6,
          "details": {
            "alive": true,
            "isProcessing": false,
            "lastTickAt": 1773253425925
          }
        },
        "telegram": {
          "ok": true,
          "latencyMs": 21,
          "details": {
            "transport": "telegram"
          }
        }
      },
      "summary": {
        "okCount": 4,
        "failCount": 0,
        "failingServices": []
      }
    },
    {
      "runId": "1e47c8e6-c0cb-4a1f-bb21-6a047bc02978",
      "reason": "scheduled",
      "startedAt": "2026-03-11T18:14:45.150Z",
      "finishedAt": "2026-03-11T18:14:45.311Z",
      "durationMs": 161,
      "overallStatus": "ok",
      "services": {
        "server": {
          "ok": true,
          "latencyMs": 161,
          "details": {
            "latencyMs": 146,
            "status": 200
          }
        },
        "opey": {
          "ok": true,
          "latencyMs": 7,
          "details": {
            "alive": true,
            "currentTicketId": null,
            "lastPollAt": 1773252857896
          }
        },
        "tidy": {
          "ok": true,
          "latencyMs": 6,
          "details": {
            "alive": true,
            "isProcessing": false,
            "lastTickAt": 1773252825844
          }
        },
        "telegram": {
          "ok": true,
          "latencyMs": 22,
          "details": {
            "transport": "telegram"
          }
        }
      },
      "summary": {
        "okCount": 4,
        "failCount": 0,
        "failingServices": []
      }
    },
    {
      "runId": "a89f9822-c7c9-44e4-be49-fbc5956bdaaf",
      "reason": "scheduled",
      "startedAt": "2026-03-11T18:04:45.144Z",
      "finishedAt": "2026-03-11T18:04:45.293Z",
      "durationMs": 149,
      "overallStatus": "ok",
      "services": {
        "server": {
          "ok": true,
          "latencyMs": 149,
          "details": {
            "latencyMs": 138,
            "status": 200
          }
        },
        "opey": {
          "ok": true,
          "latencyMs": 7,
          "details": {
            "alive": true,
            "currentTicketId": null,
            "lastPollAt": 1773252257747
          }
        },
        "tidy": {
          "ok": true,
          "latencyMs": 7,
          "details": {
            "alive": true,
            "isProcessing": false,
            "lastTickAt": 1773252225758
          }
        },
        "telegram": {
          "ok": true,
          "latencyMs": 22,
          "details": {
            "transport": "telegram"
          }
        }
      },
      "summary": {
        "okCount": 4,
        "failCount": 0,
        "failingServices": []
      }
    },
    {
      "runId": "f9d70a27-e873-45d2-a14c-aad96648b594",
      "reason": "scheduled",
      "startedAt": "2026-03-11T17:54:45.142Z",
      "finishedAt": "2026-03-11T17:54:45.356Z",
      "durationMs": 214,
      "overallStatus": "ok",
      "services": {
        "server": {
          "ok": true,
          "latencyMs": 214,
          "details": {
            "latencyMs": 196,
            "status": 200
          }
        },
        "opey": {
          "ok": true,
          "latencyMs": 11,
          "details": {
            "alive": true,
            "currentTicketId": null,
            "lastPollAt": 1773251657627
          }
        },
        "tidy": {
          "ok": true,
          "latencyMs": 11,
          "details": {
            "alive": true,
            "isProcessing": false,
            "lastTickAt": 1773251625676
          }
        },
        "telegram": {
          "ok": true,
          "latencyMs": 40,
          "details": {
            "transport": "telegram"
          }
        }
      },
      "summary": {
        "okCount": 4,
        "failCount": 0,
        "failingServices": []
      }
    },
    {
      "runId": "72cdee02-f3f6-4371-9c57-720da80b16fa",
      "reason": "scheduled",
      "startedAt": "2026-03-11T17:44:45.129Z",
      "finishedAt": "2026-03-11T17:44:45.545Z",
      "durationMs": 416,
      "overallStatus": "ok",
      "services": {
        "server": {
          "ok": true,
          "latencyMs": 416,
          "details": {
            "latencyMs": 405,
            "status": 200
          }
        },
        "opey": {
          "ok": true,
          "latencyMs": 20,
          "details": {
            "alive": true,
            "currentTicketId": null,
            "lastPollAt": 1773251057478
          }
        },
        "tidy": {
          "ok": true,
          "latencyMs": 20,
          "details": {
            "alive": true,
            "isProcessing": false,
            "lastTickAt": 1773251025585
          }
        },
        "telegram": {
          "ok": true,
          "latencyMs": 20,
          "details": {
            "transport": "telegram"
          }
        }
      },
      "summary": {
        "okCount": 4,
        "failCount": 0,
        "failingServices": []
      }
    },
    {
      "runId": "2755487b-f77c-4318-9271-f17dff10c816",
      "reason": "scheduled",
      "startedAt": "2026-03-11T17:34:45.118Z",
      "finishedAt": "2026-03-11T17:34:45.271Z",
      "durationMs": 153,
      "overallStatus": "ok",
      "services": {
        "server": {
          "ok": true,
          "latencyMs": 152,
          "details": {
            "latencyMs": 137,
            "status": 200
          }
        },
        "opey": {
          "ok": true,
          "latencyMs": 7,
          "details": {
            "alive": true,
            "currentTicketId": null,
            "lastPollAt": 1773250457271
          }
        },
        "tidy": {
          "ok": true,
          "latencyMs": 6,
          "details": {
            "alive": true,
            "isProcessing": false,
            "lastTickAt": 1773250425519
          }
        },
        "telegram": {
          "ok": true,
          "latencyMs": 28,
          "details": {
            "transport": "telegram"
          }
        }
      },
      "summary": {
        "okCount": 4,
        "failCount": 0,
        "failingServices": []
      }
    },
    {
      "runId": "a6e49965-5553-4a0b-ac9f-205a13229a77",
      "reason": "scheduled",
      "startedAt": "2026-03-11T17:24:45.117Z",
      "finishedAt": "2026-03-11T17:24:45.292Z",
      "durationMs": 175,
      "overallStatus": "ok",
      "services": {
        "server": {
          "ok": true,
          "latencyMs": 175,
          "details": {
            "latencyMs": 162,
            "status": 200
          }
        },
        "opey": {
          "ok": true,
          "latencyMs": 6,
          "details": {
            "alive": true,
            "currentTicketId": null,
            "lastPollAt": 1773249857131
          }
        },
        "tidy": {
          "ok": true,
          "latencyMs": 6,
          "details": {
            "alive": true,
            "isProcessing": false,
            "lastTickAt": 1773249825455
          }
        },
        "telegram": {
          "ok": true,
          "latencyMs": 21,
          "details": {
            "transport": "telegram"
          }
        }
      },
      "summary": {
        "okCount": 4,
        "failCount": 0,
        "failingServices": []
      }
    },
    {
      "runId": "229ebad9-d529-4c95-b318-4f5e6d5eac9f",
      "reason": "scheduled",
      "startedAt": "2026-03-11T17:14:45.114Z",
      "finishedAt": "2026-03-11T17:14:45.314Z",
      "durationMs": 200,
      "overallStatus": "ok",
      "services": {
        "server": {
          "ok": true,
          "latencyMs": 200,
          "details": {
            "latencyMs": 187,
            "status": 200
          }
        },
        "opey": {
          "ok": true,
          "latencyMs": 21,
          "details": {
            "alive": true,
            "currentTicketId": null,
            "lastPollAt": 1773249256963
          }
        },
        "tidy": {
          "ok": true,
          "latencyMs": 21,
          "details": {
            "alive": true,
            "isProcessing": false,
            "lastTickAt": 1773249225372
          }
        },
        "telegram": {
          "ok": true,
          "latencyMs": 21,
          "details": {
            "transport": "telegram"
          }
        }
      },
      "summary": {
        "okCount": 4,
        "failCount": 0,
        "failingServices": []
      }
    },
    {
      "runId": "758662a2-627f-45d3-98ee-fc803f3b6890",
      "reason": "scheduled",
      "startedAt": "2026-03-11T17:04:45.108Z",
      "finishedAt": "2026-03-11T17:04:45.496Z",
      "durationMs": 388,
      "overallStatus": "ok",
      "services": {
        "server": {
          "ok": true,
          "latencyMs": 388,
          "details": {
            "latencyMs": 374,
            "status": 200
          }
        },
        "opey": {
          "ok": true,
          "latencyMs": 7,
          "details": {
            "alive": true,
            "currentTicketId": null,
            "lastPollAt": 1773248656852
          }
        },
        "tidy": {
          "ok": true,
          "latencyMs": 7,
          "details": {
            "alive": true,
            "isProcessing": false,
            "lastTickAt": 1773248625291
          }
        },
        "telegram": {
          "ok": true,
          "latencyMs": 24,
          "details": {
            "transport": "telegram"
          }
        }
      },
      "summary": {
        "okCount": 4,
        "failCount": 0,
        "failingServices": []
      }
    },
    {
      "runId": "4bca0c18-3205-45d8-9369-785f343010f2",
      "reason": "scheduled",
      "startedAt": "2026-03-11T16:54:45.102Z",
      "finishedAt": "2026-03-11T16:54:45.354Z",
      "durationMs": 252,
      "overallStatus": "ok",
      "services": {
        "server": {
          "ok": true,
          "latencyMs": 252,
          "details": {
            "latencyMs": 239,
            "status": 200
          }
        },
        "opey": {
          "ok": true,
          "latencyMs": 21,
          "details": {
            "alive": true,
            "currentTicketId": null,
            "lastPollAt": 1773248056689
          }
        },
        "tidy": {
          "ok": true,
          "latencyMs": 21,
          "details": {
            "alive": true,
            "isProcessing": false,
            "lastTickAt": 1773248025199
          }
        },
        "telegram": {
          "ok": true,
          "latencyMs": 22,
          "details": {
            "transport": "telegram"
          }
        }
      },
      "summary": {
        "okCount": 4,
        "failCount": 0,
        "failingServices": []
      }
    },
    {
      "runId": "6ba2f9d4-4489-4a98-8e7b-238cac79b49d",
      "reason": "scheduled",
      "startedAt": "2026-03-11T16:44:45.093Z",
      "finishedAt": "2026-03-11T16:44:45.252Z",
      "durationMs": 159,
      "overallStatus": "ok",
      "services": {
        "server": {
          "ok": true,
          "latencyMs": 159,
          "details": {
            "latencyMs": 147,
            "status": 200
          }
        },
        "opey": {
          "ok": true,
          "latencyMs": 20,
          "details": {
            "alive": true,
            "currentTicketId": null,
            "lastPollAt": 1773247456511
          }
        },
        "tidy": {
          "ok": true,
          "latencyMs": 19,
          "details": {
            "alive": true,
            "isProcessing": false,
            "lastTickAt": 1773247425128
          }
        },
        "telegram": {
          "ok": true,
          "latencyMs": 21,
          "details": {
            "transport": "telegram"
          }
        }
      },
      "summary": {
        "okCount": 4,
        "failCount": 0,
        "failingServices": []
      }
    },
    {
      "runId": "7dca3836-7afe-4952-86cb-80a2c0d0c669",
      "reason": "scheduled",
      "startedAt": "2026-03-11T16:34:45.080Z",
      "finishedAt": "2026-03-11T16:34:45.232Z",
      "durationMs": 152,
      "overallStatus": "ok",
      "services": {
        "server": {
          "ok": true,
          "latencyMs": 152,
          "details": {
            "latencyMs": 138,
            "status": 200
          }
        },
        "opey": {
          "ok": true,
          "latencyMs": 26,
          "details": {
            "alive": true,
            "currentTicketId": null,
            "lastPollAt": 1773246856363
          }
        },
        "tidy": {
          "ok": true,
          "latencyMs": 23,
          "details": {
            "alive": true,
            "isProcessing": true,
            "lastTickAt": 1773246885079
          }
        },
        "telegram": {
          "ok": true,
          "latencyMs": 26,
          "details": {
            "transport": "telegram"
          }
        }
      },
      "summary": {
        "okCount": 4,
        "failCount": 0,
        "failingServices": []
      }
    },
    {
      "runId": "014f8bbd-9be4-4f74-9b2d-53eb7421ed31",
      "reason": "scheduled",
      "startedAt": "2026-03-11T16:24:45.075Z",
      "finishedAt": "2026-03-11T16:24:45.231Z",
      "durationMs": 156,
      "overallStatus": "ok",
      "services": {
        "server": {
          "ok": true,
          "latencyMs": 156,
          "details": {
            "latencyMs": 145,
            "status": 200
          }
        },
        "opey": {
          "ok": true,
          "latencyMs": 23,
          "details": {
            "alive": true,
            "currentTicketId": null,
            "lastPollAt": 1773246256225
          }
        },
        "tidy": {
          "ok": true,
          "latencyMs": 23,
          "details": {
            "alive": true,
            "isProcessing": true,
            "lastTickAt": 1773246284996
          }
        },
        "telegram": {
          "ok": true,
          "latencyMs": 24,
          "details": {
            "transport": "telegram"
          }
        }
      },
      "summary": {
        "okCount": 4,
        "failCount": 0,
        "failingServices": []
      }
    },
    {
      "runId": "f13c8b94-856b-4982-9204-dc8c9af9fa18",
      "reason": "scheduled",
      "startedAt": "2026-03-11T16:14:45.061Z",
      "finishedAt": "2026-03-11T16:14:45.230Z",
      "durationMs": 169,
      "overallStatus": "ok",
      "services": {
        "server": {
          "ok": true,
          "latencyMs": 169,
          "details": {
            "latencyMs": 155,
            "status": 200
          }
        },
        "opey": {
          "ok": true,
          "latencyMs": 7,
          "details": {
            "alive": true,
            "currentTicketId": null,
            "lastPollAt": 1773245656045
          }
        },
        "tidy": {
          "ok": true,
          "latencyMs": 7,
          "details": {
            "alive": true,
            "isProcessing": true,
            "lastTickAt": 1773245684951
          }
        },
        "telegram": {
          "ok": true,
          "latencyMs": 20,
          "details": {
            "transport": "telegram"
          }
        }
      },
      "summary": {
        "okCount": 4,
        "failCount": 0,
        "failingServices": []
      }
    },
    {
      "runId": "a7e2b271-3dd1-4b6c-b4b0-8b7e55ff007d",
      "reason": "scheduled",
      "startedAt": "2026-03-11T16:04:45.058Z",
      "finishedAt": "2026-03-11T16:04:45.239Z",
      "durationMs": 181,
      "overallStatus": "ok",
      "services": {
        "server": {
          "ok": true,
          "latencyMs": 181,
          "details": {
            "latencyMs": 167,
            "status": 200
          }
        },
        "opey": {
          "ok": true,
          "latencyMs": 27,
          "details": {
            "alive": true,
            "currentTicketId": null,
            "lastPollAt": 1773245055932
          }
        },
        "tidy": {
          "ok": true,
          "latencyMs": 28,
          "details": {
            "alive": true,
            "isProcessing": false,
            "lastTickAt": 1773245084905
          }
        },
        "telegram": {
          "ok": true,
          "latencyMs": 28,
          "details": {
            "transport": "telegram"
          }
        }
      },
      "summary": {
        "okCount": 4,
        "failCount": 0,
        "failingServices": []
      }
    },
    {
      "runId": "393cf841-fada-49ca-add7-5100170faded",
      "reason": "scheduled",
      "startedAt": "2026-03-11T15:54:45.055Z",
      "finishedAt": "2026-03-11T15:54:45.213Z",
      "durationMs": 158,
      "overallStatus": "ok",
      "services": {
        "server": {
          "ok": true,
          "latencyMs": 157,
          "details": {
            "latencyMs": 139,
            "status": 200
          }
        },
        "opey": {
          "ok": true,
          "latencyMs": 10,
          "details": {
            "alive": true,
            "currentTicketId": null,
            "lastPollAt": 1773244455790
          }
        },
        "tidy": {
          "ok": true,
          "latencyMs": 8,
          "details": {
            "alive": true,
            "isProcessing": false,
            "lastTickAt": 1773244484824
          }
        },
        "telegram": {
          "ok": true,
          "latencyMs": 30,
          "details": {
            "transport": "telegram"
          }
        }
      },
      "summary": {
        "okCount": 4,
        "failCount": 0,
        "failingServices": []
      }
    },
    {
      "runId": "e3c540dc-d844-440f-8ae5-098208745161",
      "reason": "scheduled",
      "startedAt": "2026-03-11T15:44:45.052Z",
      "finishedAt": "2026-03-11T15:44:45.225Z",
      "durationMs": 173,
      "overallStatus": "ok",
      "services": {
        "server": {
          "ok": true,
          "latencyMs": 172,
          "details": {
            "latencyMs": 157,
            "status": 200
          }
        },
        "opey": {
          "ok": true,
          "latencyMs": 27,
          "details": {
            "alive": true,
            "currentTicketId": null,
            "lastPollAt": 1773243855633
          }
        },
        "tidy": {
          "ok": true,
          "latencyMs": 27,
          "details": {
            "alive": true,
            "isProcessing": false,
            "lastTickAt": 1773243884743
          }
        },
        "telegram": {
          "ok": true,
          "latencyMs": 27,
          "details": {
            "transport": "telegram"
          }
        }
      },
      "summary": {
        "okCount": 4,
        "failCount": 0,
        "failingServices": []
      }
    },
    {
      "runId": "502578b1-14a1-4076-ad16-761fdb0269fb",
      "reason": "scheduled",
      "startedAt": "2026-03-11T15:34:45.042Z",
      "finishedAt": "2026-03-11T15:34:45.264Z",
      "durationMs": 222,
      "overallStatus": "ok",
      "services": {
        "server": {
          "ok": true,
          "latencyMs": 221,
          "details": {
            "latencyMs": 205,
            "status": 200
          }
        },
        "opey": {
          "ok": true,
          "latencyMs": 8,
          "details": {
            "alive": true,
            "currentTicketId": null,
            "lastPollAt": 1773243255506
          }
        },
        "tidy": {
          "ok": true,
          "latencyMs": 8,
          "details": {
            "alive": true,
            "isProcessing": false,
            "lastTickAt": 1773243284668
          }
        },
        "telegram": {
          "ok": true,
          "latencyMs": 34,
          "details": {
            "transport": "telegram"
          }
        }
      },
      "summary": {
        "okCount": 4,
        "failCount": 0,
        "failingServices": []
      }
    },
    {
      "runId": "3a0d372c-ae77-493e-b7a5-6eabaac2d9cb",
      "reason": "scheduled",
      "startedAt": "2026-03-11T15:24:45.035Z",
      "finishedAt": "2026-03-11T15:24:45.289Z",
      "durationMs": 254,
      "overallStatus": "ok",
      "services": {
        "server": {
          "ok": true,
          "latencyMs": 254,
          "details": {
            "latencyMs": 241,
            "status": 200
          }
        },
        "opey": {
          "ok": true,
          "latencyMs": 22,
          "details": {
            "alive": true,
            "currentTicketId": null,
            "lastPollAt": 1773242655361
          }
        },
        "tidy": {
          "ok": true,
          "latencyMs": 22,
          "details": {
            "alive": true,
            "isProcessing": false,
            "lastTickAt": 1773242684585
          }
        },
        "telegram": {
          "ok": true,
          "latencyMs": 22,
          "details": {
            "transport": "telegram"
          }
        }
      },
      "summary": {
        "okCount": 4,
        "failCount": 0,
        "failingServices": []
      }
    },
    {
      "runId": "28554bf1-e6f0-499d-8365-a83b57aea27c",
      "reason": "scheduled",
      "startedAt": "2026-03-11T15:14:45.025Z",
      "finishedAt": "2026-03-11T15:14:45.229Z",
      "durationMs": 204,
      "overallStatus": "ok",
      "services": {
        "server": {
          "ok": true,
          "latencyMs": 204,
          "details": {
            "latencyMs": 192,
            "status": 200
          }
        },
        "opey": {
          "ok": true,
          "latencyMs": 6,
          "details": {
            "alive": true,
            "currentTicketId": null,
            "lastPollAt": 1773242055189
          }
        },
        "tidy": {
          "ok": true,
          "latencyMs": 22,
          "details": {
            "alive": true,
            "isProcessing": false,
            "lastTickAt": 1773242084514
          }
        },
        "telegram": {
          "ok": true,
          "latencyMs": 22,
          "details": {
            "transport": "telegram"
          }
        }
      },
      "summary": {
        "okCount": 4,
        "failCount": 0,
        "failingServices": []
      }
    },
    {
      "runId": "e89398de-a00e-4413-9310-34f76af9808d",
      "reason": "scheduled",
      "startedAt": "2026-03-11T15:04:45.020Z",
      "finishedAt": "2026-03-11T15:04:45.189Z",
      "durationMs": 169,
      "overallStatus": "ok",
      "services": {
        "server": {
          "ok": true,
          "latencyMs": 169,
          "details": {
            "latencyMs": 157,
            "status": 200
          }
        },
        "opey": {
          "ok": true,
          "latencyMs": 8,
          "details": {
            "alive": true,
            "currentTicketId": null,
            "lastPollAt": 1773241455067
          }
        },
        "tidy": {
          "ok": true,
          "latencyMs": 8,
          "details": {
            "alive": true,
            "isProcessing": false,
            "lastTickAt": 1773241484422
          }
        },
        "telegram": {
          "ok": true,
          "latencyMs": 25,
          "details": {
            "transport": "telegram"
          }
        }
      },
      "summary": {
        "okCount": 4,
        "failCount": 0,
        "failingServices": []
      }
    },
    {
      "runId": "090a51aa-cbcd-48f9-813b-6444580c5e29",
      "reason": "scheduled",
      "startedAt": "2026-03-11T14:54:45.002Z",
      "finishedAt": "2026-03-11T14:54:45.162Z",
      "durationMs": 160,
      "overallStatus": "ok",
      "services": {
        "server": {
          "ok": true,
          "latencyMs": 160,
          "details": {
            "latencyMs": 146,
            "status": 200
          }
        },
        "opey": {
          "ok": true,
          "latencyMs": 6,
          "details": {
            "alive": true,
            "currentTicketId": null,
            "lastPollAt": 1773240884891
          }
        },
        "tidy": {
          "ok": true,
          "latencyMs": 23,
          "details": {
            "alive": true,
            "isProcessing": false,
            "lastTickAt": 1773240884328
          }
        },
        "telegram": {
          "ok": true,
          "latencyMs": 23,
          "details": {
            "transport": "telegram"
          }
        }
      },
      "summary": {
        "okCount": 4,
        "failCount": 0,
        "failingServices": []
      }
    },
    {
      "runId": "34b090b5-14d1-4b45-a0d5-250360f82dfb",
      "reason": "scheduled",
      "startedAt": "2026-03-11T14:44:45.000Z",
      "finishedAt": "2026-03-11T14:44:45.361Z",
      "durationMs": 361,
      "overallStatus": "ok",
      "services": {
        "server": {
          "ok": true,
          "latencyMs": 360,
          "details": {
            "latencyMs": 340,
            "status": 200
          }
        },
        "opey": {
          "ok": true,
          "latencyMs": 26,
          "details": {
            "alive": true,
            "currentTicketId": null,
            "lastPollAt": 1773240284769
          }
        },
        "tidy": {
          "ok": true,
          "latencyMs": 26,
          "details": {
            "alive": true,
            "isProcessing": false,
            "lastTickAt": 1773240284242
          }
        },
        "telegram": {
          "ok": true,
          "latencyMs": 25,
          "details": {
            "transport": "telegram"
          }
        }
      },
      "summary": {
        "okCount": 4,
        "failCount": 0,
        "failingServices": []
      }
    },
    {
      "runId": "76763824-8435-435f-9b2c-d719ecedfaf6",
      "reason": "scheduled",
      "startedAt": "2026-03-11T14:35:00.027Z",
      "finishedAt": "2026-03-11T14:35:00.204Z",
      "durationMs": 177,
      "overallStatus": "ok",
      "services": {
        "server": {
          "ok": true,
          "latencyMs": 177,
          "details": {
            "latencyMs": 160,
            "status": 200
          }
        },
        "opey": {
          "ok": true,
          "latencyMs": 23,
          "details": {
            "alive": true,
            "currentTicketId": null,
            "lastPollAt": 1773239684619
          }
        },
        "tidy": {
          "ok": true,
          "latencyMs": 23,
          "details": {
            "alive": true,
            "isProcessing": false,
            "lastTickAt": 1773239684175
          }
        },
        "telegram": {
          "ok": true,
          "latencyMs": 23,
          "details": {
            "transport": "telegram"
          }
        }
      },
      "summary": {
        "okCount": 4,
        "failCount": 0,
        "failingServices": []
      }
    },
    {
      "runId": "69a8e73e-5077-405a-a83d-182134e5a8b6",
      "reason": "scheduled",
      "startedAt": "2026-03-11T14:33:56.396Z",
      "finishedAt": "2026-03-11T14:33:56.580Z",
      "durationMs": 184,
      "overallStatus": "ok",
      "services": {
        "server": {
          "ok": true,
          "latencyMs": 183,
          "details": {
            "latencyMs": 161,
            "status": 200
          }
        },
        "opey": {
          "ok": true,
          "latencyMs": 8,
          "details": {
            "alive": true,
            "currentTicketId": null,
            "lastPollAt": 1773239623474
          }
        },
        "tidy": {
          "ok": true,
          "latencyMs": 9,
          "details": {
            "alive": true,
            "isProcessing": false,
            "lastTickAt": 1773239622574
          }
        },
        "telegram": {
          "ok": true,
          "latencyMs": 26,
          "details": {
            "transport": "telegram"
          }
        }
      },
      "summary": {
        "okCount": 4,
        "failCount": 0,
        "failingServices": []
      }
    },
    {
      "runId": "5ea9ccad-c6d1-4ab5-90a4-c6e1f72a06fd",
      "reason": "scheduled",
      "startedAt": "2026-03-11T14:32:45.204Z",
      "finishedAt": "2026-03-11T14:32:45.595Z",
      "durationMs": 391,
      "overallStatus": "ok",
      "services": {
        "server": {
          "ok": true,
          "latencyMs": 390,
          "details": {
            "latencyMs": 363,
            "status": 200
          }
        },
        "opey": {
          "ok": true,
          "latencyMs": 10,
          "details": {
            "alive": true,
            "currentTicketId": null,
            "lastPollAt": 1773239563461
          }
        },
        "tidy": {
          "ok": true,
          "latencyMs": 10,
          "details": {
            "alive": true,
            "isProcessing": false,
            "lastTickAt": 1773239562561
          }
        },
        "telegram": {
          "ok": true,
          "latencyMs": 31,
          "details": {
            "transport": "telegram"
          }
        }
      },
      "summary": {
        "okCount": 4,
        "failCount": 0,
        "failingServices": []
      }
    },
    {
      "runId": "98a6b292-d2f1-43aa-a7ac-3442c7286ae5",
      "reason": "scheduled",
      "startedAt": "2026-03-11T14:27:41.164Z",
      "finishedAt": "2026-03-11T14:27:41.356Z",
      "durationMs": 192,
      "overallStatus": "ok",
      "services": {
        "server": {
          "ok": true,
          "latencyMs": 191,
          "details": {
            "latencyMs": 166,
            "status": 200
          }
        },
        "opey": {
          "ok": true,
          "latencyMs": 10,
          "details": {
            "alive": true,
            "currentTicketId": null,
            "lastPollAt": 1773239233364
          }
        },
        "tidy": {
          "ok": true,
          "latencyMs": 9,
          "details": {
            "alive": true,
            "isProcessing": false,
            "lastTickAt": 1773239202535
          }
        },
        "telegram": {
          "ok": true,
          "latencyMs": 27,
          "details": {
            "transport": "telegram"
          }
        }
      },
      "summary": {
        "okCount": 4,
        "failCount": 0,
        "failingServices": []
      }
    },
    {
      "runId": "07f24f8e-9b45-4163-b533-f015704acd3a",
      "reason": "scheduled",
      "startedAt": "2026-03-11T14:22:34.250Z",
      "finishedAt": "2026-03-11T14:22:34.444Z",
      "durationMs": 194,
      "overallStatus": "ok",
      "services": {
        "server": {
          "ok": true,
          "latencyMs": 193,
          "details": {
            "latencyMs": 169,
            "status": 200
          }
        },
        "opey": {
          "ok": true,
          "latencyMs": 10,
          "details": {
            "alive": true,
            "currentTicketId": null,
            "lastPollAt": 1773238933297
          }
        },
        "tidy": {
          "ok": true,
          "latencyMs": 10,
          "details": {
            "alive": true,
            "isProcessing": false,
            "lastTickAt": 1773238902499
          }
        },
        "telegram": {
          "ok": true,
          "latencyMs": 27,
          "details": {
            "transport": "telegram"
          }
        }
      },
      "summary": {
        "okCount": 4,
        "failCount": 0,
        "failingServices": []
      }
    },
    {
      "runId": "3d749ddd-cf4d-475e-bcd1-d4f2e8bf9277",
      "reason": "scheduled",
      "startedAt": "2026-03-11T14:19:39.922Z",
      "finishedAt": "2026-03-11T14:19:40.171Z",
      "durationMs": 249,
      "overallStatus": "ok",
      "services": {
        "server": {
          "ok": true,
          "latencyMs": 249,
          "details": {
            "latencyMs": 235,
            "status": 200
          }
        },
        "opey": {
          "ok": true,
          "latencyMs": 7,
          "details": {
            "alive": true,
            "currentTicketId": null,
            "lastPollAt": 1773238753260
          }
        },
        "tidy": {
          "ok": true,
          "latencyMs": 7,
          "details": {
            "alive": true,
            "isProcessing": false,
            "lastTickAt": 1773238722483
          }
        },
        "telegram": {
          "ok": true,
          "latencyMs": 25,
          "details": {
            "transport": "telegram"
          }
        }
      },
      "summary": {
        "okCount": 4,
        "failCount": 0,
        "failingServices": []
      }
    },
    {
      "runId": "b773ce70-3da5-45f2-a105-4c8d7c1226b7",
      "reason": "scheduled",
      "startedAt": "2026-03-11T14:09:54.948Z",
      "finishedAt": "2026-03-11T14:09:55.100Z",
      "durationMs": 152,
      "overallStatus": "ok",
      "services": {
        "server": {
          "ok": true,
          "latencyMs": 151,
          "details": {
            "latencyMs": 133,
            "status": 200
          }
        },
        "opey": {
          "ok": true,
          "latencyMs": 8,
          "details": {
            "alive": true,
            "currentTicketId": null,
            "lastPollAt": 1773238183145
          }
        },
        "tidy": {
          "ok": true,
          "latencyMs": 24,
          "details": {
            "alive": true,
            "isProcessing": false,
            "lastTickAt": 1773238182430
          }
        },
        "telegram": {
          "ok": true,
          "latencyMs": 24,
          "details": {
            "transport": "telegram"
          }
        }
      },
      "summary": {
        "okCount": 4,
        "failCount": 0,
        "failingServices": []
      }
    },
    {
      "runId": "d2893719-1aa7-43e5-8d3b-bf7547a06202",
      "reason": "scheduled",
      "startedAt": "2026-03-11T14:02:25.882Z",
      "finishedAt": "2026-03-11T14:02:26.075Z",
      "durationMs": 193,
      "overallStatus": "ok",
      "services": {
        "server": {
          "ok": true,
          "latencyMs": 192,
          "details": {
            "latencyMs": 170,
            "status": 200
          }
        },
        "opey": {
          "ok": true,
          "latencyMs": 9,
          "details": {
            "alive": true,
            "currentTicketId": null,
            "lastPollAt": 1773237733048
          }
        },
        "tidy": {
          "ok": true,
          "latencyMs": 23,
          "details": {
            "alive": true,
            "isProcessing": false,
            "lastTickAt": 1773237702366
          }
        },
        "telegram": {
          "ok": true,
          "latencyMs": 23,
          "details": {
            "transport": "telegram"
          }
        }
      },
      "summary": {
        "okCount": 4,
        "failCount": 0,
        "failingServices": []
      }
    },
    {
      "runId": "85215869-016e-4991-8e55-91bdc014af8a",
      "reason": "scheduled",
      "startedAt": "2026-03-11T13:55:08.489Z",
      "finishedAt": "2026-03-11T13:55:08.671Z",
      "durationMs": 182,
      "overallStatus": "ok",
      "services": {
        "server": {
          "ok": true,
          "latencyMs": 182,
          "details": {
            "latencyMs": 161,
            "status": 200
          }
        },
        "opey": {
          "ok": true,
          "latencyMs": 8,
          "details": {
            "alive": true,
            "currentTicketId": null,
            "lastPollAt": 1773237282931
          }
        },
        "tidy": {
          "ok": true,
          "latencyMs": 8,
          "details": {
            "alive": true,
            "isProcessing": false,
            "lastTickAt": 1773237252421
          }
        },
        "telegram": {
          "ok": true,
          "latencyMs": 21,
          "details": {
            "transport": "telegram"
          }
        }
      },
      "summary": {
        "okCount": 4,
        "failCount": 0,
        "failingServices": []
      }
    },
    {
      "runId": "2099a3db-33cc-4c7b-81d3-62f70292a651",
      "reason": "scheduled",
      "startedAt": "2026-03-11T13:54:46.998Z",
      "finishedAt": "2026-03-11T13:54:47.196Z",
      "durationMs": 198,
      "overallStatus": "ok",
      "services": {
        "server": {
          "ok": true,
          "latencyMs": 197,
          "details": {
            "latencyMs": 174,
            "status": 200
          }
        },
        "opey": {
          "ok": true,
          "latencyMs": 9,
          "details": {
            "alive": true,
            "currentTicketId": null,
            "lastPollAt": 1773237282931
          }
        },
        "tidy": {
          "ok": true,
          "latencyMs": 8,
          "details": {
            "alive": true,
            "isProcessing": false,
            "lastTickAt": 1773237252421
          }
        },
        "telegram": {
          "ok": true,
          "latencyMs": 27,
          "details": {
            "transport": "telegram"
          }
        }
      },
      "summary": {
        "okCount": 4,
        "failCount": 0,
        "failingServices": []
      }
    },
    {
      "runId": "897d3056-8e33-44ad-9633-698bf5d6942f",
      "reason": "scheduled",
      "startedAt": "2026-03-11T13:53:34.259Z",
      "finishedAt": "2026-03-11T13:53:34.448Z",
      "durationMs": 189,
      "overallStatus": "ok",
      "services": {
        "server": {
          "ok": true,
          "latencyMs": 188,
          "details": {
            "latencyMs": 165,
            "status": 200
          }
        },
        "opey": {
          "ok": true,
          "latencyMs": 9,
          "details": {
            "alive": true,
            "currentTicketId": null,
            "lastPollAt": 1773237192902
          }
        },
        "tidy": {
          "ok": true,
          "latencyMs": 9,
          "details": {
            "alive": true,
            "isProcessing": false,
            "lastTickAt": 1773237192407
          }
        },
        "telegram": {
          "ok": true,
          "latencyMs": 25,
          "details": {
            "transport": "telegram"
          }
        }
      },
      "summary": {
        "okCount": 4,
        "failCount": 0,
        "failingServices": []
      }
    },
    {
      "runId": "0d3a6cf9-3655-4cd7-921a-41d67e7c2fde",
      "reason": "manual",
      "requestedBy": "kayley",
      "startedAt": "2026-03-11T13:49:32.735Z",
      "finishedAt": "2026-03-11T13:49:32.908Z",
      "durationMs": 173,
      "overallStatus": "ok",
      "services": {
        "server": {
          "ok": true,
          "latencyMs": 171,
          "details": {
            "latencyMs": 160,
            "status": 200
          }
        },
        "opey": {
          "ok": true,
          "latencyMs": 7,
          "details": {
            "alive": true,
            "currentTicketId": null,
            "lastPollAt": 1773236952849
          }
        },
        "tidy": {
          "ok": true,
          "latencyMs": 8,
          "details": {
            "alive": true,
            "isProcessing": false,
            "lastTickAt": 1773236952383
          }
        },
        "telegram": {
          "ok": true,
          "latencyMs": 9,
          "details": {
            "transport": "telegram"
          }
        }
      },
      "summary": {
        "okCount": 4,
        "failCount": 0,
        "failingServices": []
      }
    },
    {
      "runId": "25003ba8-2264-4c5e-92ed-933e17759ff4",
      "reason": "scheduled",
      "startedAt": "2026-03-11T13:46:23.262Z",
      "finishedAt": "2026-03-11T13:46:23.435Z",
      "durationMs": 173,
      "overallStatus": "ok",
      "services": {
        "server": {
          "ok": true,
          "latencyMs": 172,
          "details": {
            "latencyMs": 156,
            "status": 200
          }
        },
        "opey": {
          "ok": true,
          "latencyMs": 9,
          "details": {
            "alive": true,
            "currentTicketId": null,
            "lastPollAt": 1773236772812
          }
        },
        "tidy": {
          "ok": true,
          "latencyMs": 9,
          "details": {
            "alive": true,
            "isProcessing": false,
            "lastTickAt": 1773236772354
          }
        },
        "telegram": {
          "ok": true,
          "latencyMs": 24,
          "details": {
            "transport": "telegram"
          }
        }
      },
      "summary": {
        "okCount": 4,
        "failCount": 0,
        "failingServices": []
      }
    },
    {
      "runId": "165d5e8b-87fe-4a1d-b4c7-33be0a90b498",
      "reason": "scheduled",
      "startedAt": "2026-03-11T13:36:23.249Z",
      "finishedAt": "2026-03-11T13:36:23.421Z",
      "durationMs": 172,
      "overallStatus": "ok",
      "services": {
        "server": {
          "ok": true,
          "latencyMs": 171,
          "details": {
            "latencyMs": 159,
            "status": 200
          }
        },
        "opey": {
          "ok": true,
          "latencyMs": 5,
          "details": {
            "alive": true,
            "currentTicketId": null,
            "lastPollAt": 1773236172682
          }
        },
        "tidy": {
          "ok": true,
          "latencyMs": 23,
          "details": {
            "alive": true,
            "isProcessing": false,
            "lastTickAt": 1773236172324
          }
        },
        "telegram": {
          "ok": true,
          "latencyMs": 23,
          "details": {
            "transport": "telegram"
          }
        }
      },
      "summary": {
        "okCount": 4,
        "failCount": 0,
        "failingServices": []
      }
    },
    {
      "runId": "193ce2fa-1808-46aa-82a8-9d06fb35ee5a",
      "reason": "scheduled",
      "startedAt": "2026-03-11T13:26:38.270Z",
      "finishedAt": "2026-03-11T13:26:38.502Z",
      "durationMs": 232,
      "overallStatus": "ok",
      "services": {
        "server": {
          "ok": true,
          "latencyMs": 229,
          "details": {
            "latencyMs": 177,
            "status": 200
          }
        },
        "opey": {
          "ok": true,
          "latencyMs": 22,
          "details": {
            "alive": true,
            "currentTicketId": null,
            "lastPollAt": 1773235572551
          }
        },
        "tidy": {
          "ok": true,
          "latencyMs": 59,
          "details": {
            "alive": true,
            "isProcessing": true,
            "lastTickAt": 1773235572264
          }
        },
        "telegram": {
          "ok": true,
          "latencyMs": 58,
          "details": {
            "transport": "telegram"
          }
        }
      },
      "summary": {
        "okCount": 4,
        "failCount": 0,
        "failingServices": []
      }
    },
    {
      "runId": "0b2224cf-8eea-4f24-9abe-1b4b6bbd0556",
      "reason": "scheduled",
      "startedAt": "2026-03-11T04:23:30.419Z",
      "finishedAt": "2026-03-11T04:23:30.683Z",
      "durationMs": 264,
      "overallStatus": "ok",
      "services": {
        "server": {
          "ok": true,
          "latencyMs": 263,
          "details": {
            "latencyMs": 251,
            "status": 200
          }
        },
        "opey": {
          "ok": true,
          "latencyMs": 7,
          "details": {
            "alive": true,
            "currentTicketId": null,
            "lastPollAt": 1773202994247
          }
        },
        "tidy": {
          "ok": true,
          "latencyMs": 23,
          "details": {
            "alive": true,
            "isProcessing": false,
            "lastTickAt": 1773202998878
          }
        },
        "telegram": {
          "ok": true,
          "latencyMs": 23,
          "details": {
            "transport": "telegram"
          }
        }
      },
      "summary": {
        "okCount": 4,
        "failCount": 0,
        "failingServices": []
      }
    },
    {
      "runId": "bda721a1-d741-4dfa-9d5a-c5085e9770fc",
      "reason": "scheduled",
      "startedAt": "2026-03-11T04:13:30.414Z",
      "finishedAt": "2026-03-11T04:13:30.693Z",
      "durationMs": 279,
      "overallStatus": "ok",
      "services": {
        "server": {
          "ok": true,
          "latencyMs": 279,
          "details": {
            "latencyMs": 265,
            "status": 200
          }
        },
        "opey": {
          "ok": true,
          "latencyMs": 6,
          "details": {
            "alive": true,
            "currentTicketId": null,
            "lastPollAt": 1773202394106
          }
        },
        "tidy": {
          "ok": true,
          "latencyMs": 25,
          "details": {
            "alive": true,
            "isProcessing": false,
            "lastTickAt": 1773202398786
          }
        },
        "telegram": {
          "ok": true,
          "latencyMs": 25,
          "details": {
            "transport": "telegram"
          }
        }
      },
      "summary": {
        "okCount": 4,
        "failCount": 0,
        "failingServices": []
      }
    },
    {
      "runId": "6a253a08-35a7-46f3-9778-4f6f74348e7f",
      "reason": "scheduled",
      "startedAt": "2026-03-11T04:03:30.406Z",
      "finishedAt": "2026-03-11T04:03:30.554Z",
      "durationMs": 148,
      "overallStatus": "ok",
      "services": {
        "server": {
          "ok": true,
          "latencyMs": 148,
          "details": {
            "latencyMs": 132,
            "status": 200
          }
        },
        "opey": {
          "ok": true,
          "latencyMs": 23,
          "details": {
            "alive": true,
            "currentTicketId": null,
            "lastPollAt": 1773201793948
          }
        },
        "tidy": {
          "ok": true,
          "latencyMs": 23,
          "details": {
            "alive": true,
            "isProcessing": false,
            "lastTickAt": 1773201798741
          }
        },
        "telegram": {
          "ok": true,
          "latencyMs": 23,
          "details": {
            "transport": "telegram"
          }
        }
      },
      "summary": {
        "okCount": 4,
        "failCount": 0,
        "failingServices": []
      }
    },
    {
      "runId": "0a3a8ba6-7884-4a47-8cd9-35afcecb52e7",
      "reason": "scheduled",
      "startedAt": "2026-03-11T03:53:30.395Z",
      "finishedAt": "2026-03-11T03:53:30.580Z",
      "durationMs": 185,
      "overallStatus": "ok",
      "services": {
        "server": {
          "ok": true,
          "latencyMs": 184,
          "details": {
            "latencyMs": 169,
            "status": 200
          }
        },
        "opey": {
          "ok": true,
          "latencyMs": 8,
          "details": {
            "alive": true,
            "currentTicketId": null,
            "lastPollAt": 1773201193784
          }
        },
        "tidy": {
          "ok": true,
          "latencyMs": 8,
          "details": {
            "alive": true,
            "isProcessing": false,
            "lastTickAt": 1773201198679
          }
        },
        "telegram": {
          "ok": true,
          "latencyMs": 26,
          "details": {
            "transport": "telegram"
          }
        }
      },
      "summary": {
        "okCount": 4,
        "failCount": 0,
        "failingServices": []
      }
    },
    {
      "runId": "1b11d676-5fd2-4337-b6e2-6f8ce6707410",
      "reason": "scheduled",
      "startedAt": "2026-03-11T03:43:30.389Z",
      "finishedAt": "2026-03-11T03:43:30.538Z",
      "durationMs": 149,
      "overallStatus": "ok",
      "services": {
        "server": {
          "ok": true,
          "latencyMs": 149,
          "details": {
            "latencyMs": 134,
            "status": 200
          }
        },
        "opey": {
          "ok": true,
          "latencyMs": 7,
          "details": {
            "alive": true,
            "currentTicketId": null,
            "lastPollAt": 1773200593615
          }
        },
        "tidy": {
          "ok": true,
          "latencyMs": 7,
          "details": {
            "alive": true,
            "isProcessing": false,
            "lastTickAt": 1773200598594
          }
        },
        "telegram": {
          "ok": true,
          "latencyMs": 23,
          "details": {
            "transport": "telegram"
          }
        }
      },
      "summary": {
        "okCount": 4,
        "failCount": 0,
        "failingServices": []
      }
    },
    {
      "runId": "73bd38ef-19db-4b97-80c8-c16690a7b721",
      "reason": "scheduled",
      "startedAt": "2026-03-11T03:33:30.374Z",
      "finishedAt": "2026-03-11T03:33:30.597Z",
      "durationMs": 223,
      "overallStatus": "ok",
      "services": {
        "server": {
          "ok": true,
          "latencyMs": 223,
          "details": {
            "latencyMs": 209,
            "status": 200
          }
        },
        "opey": {
          "ok": true,
          "latencyMs": 22,
          "details": {
            "alive": true,
            "currentTicketId": null,
            "lastPollAt": 1773199993442
          }
        },
        "tidy": {
          "ok": true,
          "latencyMs": 23,
          "details": {
            "alive": true,
            "isProcessing": false,
            "lastTickAt": 1773199998496
          }
        },
        "telegram": {
          "ok": true,
          "latencyMs": 23,
          "details": {
            "transport": "telegram"
          }
        }
      },
      "summary": {
        "okCount": 4,
        "failCount": 0,
        "failingServices": []
      }
    }
  ]
}
